elmoformanylangs/__init__.py
elmoformanylangs/__main__.py
elmoformanylangs/biLM.py
elmoformanylangs/dataloader.py
elmoformanylangs/elmo.py
elmoformanylangs/frontend.py
elmoformanylangs/utils.py
elmoformanylangs/configs/cnn_0_100_512_4096_sample.json
elmoformanylangs/configs/cnn_50_100_512_4096_sample.json
elmoformanylangs/modules/__init__.py
elmoformanylangs/modules/classify_layer.py
elmoformanylangs/modules/elmo.py
elmoformanylangs/modules/embedding_layer.py
elmoformanylangs/modules/encoder_base.py
elmoformanylangs/modules/highway.py
elmoformanylangs/modules/lstm.py
elmoformanylangs/modules/lstm_cell_with_projection.py
elmoformanylangs/modules/token_embedder.py
elmoformanylangs/modules/util.py
elmoformanylangs-0.0.4.post2.dist-info/LICENSE
elmoformanylangs-0.0.4.post2.dist-info/METADATA
elmoformanylangs-0.0.4.post2.dist-info/WHEEL
elmoformanylangs-0.0.4.post2.dist-info/top_level.txt
elmoformanylangs-0.0.4.post2.dist-info/RECORD
